zinterface.py
zinterface-0.1.0.dist-info/LICENSE
zinterface-0.1.0.dist-info/METADATA
zinterface-0.1.0.dist-info/WHEEL
zinterface-0.1.0.dist-info/top_level.txt
zinterface-0.1.0.dist-info/RECORD
