Metadata-Version: 2.1
Name: zinterface
Version: 0.1.0
Summary: python的interface模式
Home-page: https://github.com/zlyuancn/zinterface
Author: zlyuan
Author-email: zlyuancn@163.com
License: GNU GENERAL PUBLIC LICENSE
Platform: all
Classifier: Intended Audience :: Developers
Classifier: Operating System :: OS Independent
Classifier: Programming Language :: Python
Classifier: Programming Language :: Python :: 3
